sharkiq/__init__.py
sharkiq/auth0.py
sharkiq/ayla_api.py
sharkiq/const.py
sharkiq/exc.py
sharkiq/fallback_auth.py
sharkiq/sharkiq.py
sharkiq-1.5.0.dist-info/licenses/LICENSE
sharkiq-1.5.0.dist-info/METADATA
sharkiq-1.5.0.dist-info/WHEEL
sharkiq-1.5.0.dist-info/top_level.txt
sharkiq-1.5.0.dist-info/RECORD
