Metadata-Version: 2.4
Name: sharkiq
Version: 1.5.0
Summary: Python API for Shark IQ robots
Author: sharkiqlibs Maintainers
License-Expression: MIT
Project-URL: Homepage, https://github.com/sharkiqlibs/sharkiq
Project-URL: Repository, https://github.com/sharkiqlibs/sharkiq
Project-URL: Issues, https://github.com/sharkiqlibs/sharkiq/issues
Classifier: Programming Language :: Python :: 3
Classifier: Programming Language :: Python :: 3.9
Classifier: Programming Language :: Python :: 3.10
Classifier: Programming Language :: Python :: 3.11
Classifier: Programming Language :: Python :: 3.12
Classifier: Programming Language :: Python :: 3.13
Requires-Python: >=3.9
License-File: LICENSE
Requires-Dist: aiohttp>=3.8.1
Requires-Dist: auth0-python>=4.10.0
Requires-Dist: requests>=2.27.1
Provides-Extra: test
Requires-Dist: pytest==8.4.2; extra == "test"
Requires-Dist: pytest-asyncio==1.2.0; extra == "test"
Requires-Dist: pytest-cov==7.0.0; extra == "test"
Provides-Extra: dev
Requires-Dist: pytest==8.4.2; extra == "dev"
Requires-Dist: pytest-asyncio==1.2.0; extra == "dev"
Requires-Dist: pytest-cov==7.0.0; extra == "dev"
Requires-Dist: build==1.3.0; extra == "dev"
Dynamic: license-file
